INSTALL.rst
LICENSE
MANIFEST.in
README.rst
ez_setup.py
requirements.txt
setup.cfg
setup.py
tests.py
django_projector.egg-info/PKG-INFO
django_projector.egg-info/SOURCES.txt
django_projector.egg-info/dependency_links.txt
django_projector.egg-info/not-zip-safe
django_projector.egg-info/requires.txt
django_projector.egg-info/top_level.txt
docs/Makefile
docs/authorization.rst
docs/conf.py
docs/configuration.rst
docs/index.rst
docs/installation.rst
docs/make.bat
docs/api/forms.rst
docs/api/index.rst
docs/api/managers.rst
docs/api/models.rst
docs/api/signals.rst
docs/api/utils.rst
docs/api/core/controllers.rst
docs/api/core/exceptions.rst
docs/api/core/index.rst
docs/api/views/index.rst
docs/api/views/project.rst
docs/api/views/project_repository.rst
docs/api/views/users.rst
docs/dev/testing.rst
docs/static/django-projector-01.png
docs/theme/nature/theme.conf
docs/theme/nature/static/nature.css_t
docs/theme/nature/static/pygments.css
docs/usage/example_project.rst
docs/usage/teamwork.rst
docs/usage/projects/basics.rst
docs/usage/projects/forking.rst
docs/usage/projects/index.rst
example_project/__init__.py
example_project/manage.py
example_project/settings.py
example_project/settings_test.py
example_project/urls.py
example_project/conf/__init__.py
example_project/templates/403.html
example_project/templates/404.html
example_project/templates/500.html
example_project/templates/base.html
example_project/templates/base_1col.html
example_project/templates/layout/menu_top.html
projector/__init__.py
projector/actions.py
projector/admin.py
projector/feeds.py
projector/filters.py
projector/forms.py
projector/listeners.py
projector/managers.py
projector/models.py
projector/settings.py
projector/signals.py
projector/tasks.py
projector/urls.py
projector/conf/__init__.py
projector/conf/workflow.py
projector/contrib/__init__.py
projector/contrib/git/__init__.py
projector/contrib/git/githttp.py
projector/contrib/git/urls.py
projector/contrib/git/utils.py
projector/contrib/git/views.py
projector/core/__init__.py
projector/core/controllers.py
projector/core/exceptions.py
projector/fixtures/test_data.json
projector/forks/__init__.py
projector/forks/base.py
projector/forks/bitbucket.py
projector/forks/github.py
