Metadata-Version: 1.1
Name: django-projector
Version: 0.2.0
Summary: 
